testkernel
