Metadata-Version: 1.1
Name: test-kernel
Version: 0.6.02
Summary: Test custom kernel pip installable!
Home-page: https://github.com/jcoady/test-kernel
Author: John Coady
Author-email: johncoady@shaw.ca
License: New BSD License
Keywords: python jupyter ipython kernel
Platform: UNKNOWN
Classifier: Development Status :: 4 - Beta
Classifier: Programming Language :: Python
Classifier: Framework :: IPython
Classifier: License :: OSI Approved
